pypopgenbe/__init__.py
pypopgenbe/__version__.py
pypopgenbe/generatepop.py
pypopgenbe/gp.py
pypopgenbe/popgenconsts.pkl
pypopgenbe/impl/__init__.py
pypopgenbe/impl/addstochasticvariation.py
pypopgenbe/impl/agecdf.py
pypopgenbe/impl/ageinv.py
pypopgenbe/impl/agernd.py
pypopgenbe/impl/aggregateorgans.py
pypopgenbe/impl/assignage.py
pypopgenbe/impl/assignethnicity.py
pypopgenbe/impl/assignsex.py
pypopgenbe/impl/assigntargetbodyweight.py
pypopgenbe/impl/assigntargetheight.py
pypopgenbe/impl/calculatebmi.py
pypopgenbe/impl/calculatebonemassadjustmentfactor.py
pypopgenbe/impl/calculatebrainmass.py
pypopgenbe/impl/calculateinvivoenzymerate.py
pypopgenbe/impl/calculatemass.py
pypopgenbe/impl/calculatemppgl.py
pypopgenbe/impl/calculatemusclemassadjustmentfactor.py
pypopgenbe/impl/calculateskinmass.py
pypopgenbe/impl/calculatetargetorganmass.py
pypopgenbe/impl/collateinputs.py
pypopgenbe/impl/convertenzymerateunits.py
pypopgenbe/impl/convertflowunits.py
pypopgenbe/impl/createethnicitybreaks.py
pypopgenbe/impl/decreasingsquarelyinv.py
pypopgenbe/impl/decreasingsquarelyrnd.py
pypopgenbe/impl/enum.py
pypopgenbe/impl/generatestats.py
pypopgenbe/impl/interlace.py
pypopgenbe/impl/invertindicies.py
pypopgenbe/impl/lognrnd0.py
pypopgenbe/impl/normrnd0.py
pypopgenbe/impl/poptocsv.py
pypopgenbe/impl/truncatednormrnd.py
pypopgenbe/impl/varyinvitroenzymerates.py
pypopgenbe-1.5.5.dist-info/LICENSE
pypopgenbe-1.5.5.dist-info/METADATA
pypopgenbe-1.5.5.dist-info/WHEEL
pypopgenbe-1.5.5.dist-info/top_level.txt
pypopgenbe-1.5.5.dist-info/RECORD
