Metadata-Version: 2.1
Name: pypopgenbe
Version: 1.5.5
Summary: Port of PopGen MATLAB backend
Author-email: Alex Hogg <the.hoglet@gmail.com>
Project-URL: Homepage, https://pypopgen.github.io/
Project-URL: Repository, https://github.com/PyPopGen/PyPopGenBE
Project-URL: Issues, https://github.com/PyPopGen/PyPopGenBE/issues
Project-URL: Literature, https://doi.org/10.1016/j.tox.2013.07.009
Keywords: Virtual human population generator,Population variability,QIVIVE,PBPK,Reverse dosimetry
Classifier: Development Status :: 5 - Production/Stable
Classifier: Intended Audience :: Science/Research
Classifier: Topic :: Scientific/Engineering :: Bio-Informatics
Classifier: License :: OSI Approved :: MIT License
Classifier: Programming Language :: Python :: 3.12
Requires-Python: >=3.12
License-File: LICENSE
Requires-Dist: scipy >=1.12.0
